show_h5/__init__.py
show_h5/show_h5.py
show_h5-0.2.1.dist-info/LICENSE
show_h5-0.2.1.dist-info/METADATA
show_h5-0.2.1.dist-info/WHEEL
show_h5-0.2.1.dist-info/entry_points.txt
show_h5-0.2.1.dist-info/top_level.txt
show_h5-0.2.1.dist-info/RECORD
