Metadata-Version: 2.1
Name: show-h5
Version: 0.2.1
Summary: Command-line interface to preview HDF5 files
Home-page: https://github.com/jtebert/show_h5
Author-email: julia@juliaebert.com
License: UNKNOWN
Platform: UNKNOWN
Classifier: Programming Language :: Python :: 3
Classifier: License :: OSI Approved :: MIT License
Classifier: Operating System :: OS Independent
Requires-Dist: h5py
Requires-Dist: argparse
